{
  "publicPath": "/_nuxt/",
  "all": [
    "../server/index.spa.html",
    "../server/index.ssr.html",
    "1eafbd9.js",
    "346dfa5.js",
    "7256f7e.js",
    "LICENSES",
    "d470d6c.js"
  ],
  "initial": [
    "1eafbd9.js",
    "346dfa5.js",
    "d470d6c.js"
  ],
  "async": [
    "7256f7e.js"
  ],
  "modules": {
    "13947992": [
      3
    ],
    "43835052": [
      6
    ],
    "51376695": [
      6
    ],
    "71284094": [
      3
    ],
    "78238812": [
      6
    ],
    "98d08244": [
      6
    ],
    "432b538c": [
      3
    ],
    "3c361c3e": [
      3
    ],
    "f0fe4266": [
      6
    ],
    "3bd968ba": [
      3
    ],
    "39cbbe6b": [
      3
    ],
    "aec8233e": [
      3
    ],
    "a07f128a": [
      3
    ],
    "0c951008": [
      3
    ],
    "104be22a": [
      3
    ],
    "63cc9bb9": [
      6
    ],
    "4379d7cc": [
      6
    ],
    "c46ad0f4": [
      3
    ],
    "62bed1c4": [
      3
    ],
    "2272da28": [
      3
    ],
    "236ca367": [
      3
    ],
    "e5852a80": [
      3
    ],
    "7fc663d0": [
      3
    ],
    "e288b1c6": [
      6
    ],
    "fa118c54": [
      6
    ],
    "60c160c9": [
      6
    ],
    "0aafd2f4": [
      6
    ],
    "0ac20ce4": [
      6
    ],
    "601e052b": [
      6
    ],
    "7bc580f6": [
      6
    ],
    "dc160018": [
      6
    ],
    "a7796086": [
      6
    ],
    "0ff1f744": [
      6
    ],
    "5075d076": [
      6
    ],
    "6c8b4f99": [
      6
    ],
    "6aed1580": [
      6
    ],
    "25ab4b6e": [
      6
    ],
    "0da3e036": [
      6
    ],
    "4fb4f8a4": [
      6
    ],
    "3f9a12af": [
      3
    ],
    "3d16de2c": [
      3
    ],
    "a262af5c": [
      3
    ],
    "b87b36ce": [
      6
    ],
    "67c30dd0": [
      6
    ],
    "708154f4": [
      3
    ],
    "7f75c24e": [
      3
    ],
    "80130ab4": [
      3
    ],
    "6cf47003": [
      3
    ],
    "8da5bb44": [
      3
    ],
    "60a031a2": [
      3
    ],
    "6899adce": [
      3
    ],
    "6fee6f2c": [
      3
    ],
    "08ba1d6e": [
      6
    ],
    "0c3d562c": [
      3
    ],
    "4b9eba14": [
      3
    ],
    "2fba8212": [
      3
    ],
    "434f7fe0": [
      3
    ],
    "10b82745": [
      3
    ],
    "74b35602": [
      3
    ],
    "2fb7fab0": [
      3
    ],
    "38a3e41c": [
      3
    ],
    "4b63dbbb": [
      3
    ],
    "923b5868": [
      3
    ],
    "9741a0a0": [
      3
    ],
    "c9aa8370": [
      3
    ],
    "5f030349": [
      3
    ],
    "7731732e": [
      3
    ],
    "d1eec9ac": [
      3
    ],
    "25ab083b": [
      3
    ],
    "13b44ff2": [
      3
    ],
    "13b8dba8": [
      3
    ],
    "13c1f314": [
      3
    ],
    "2279da31": [
      3
    ],
    "4fc4cccb": [
      3
    ],
    "827444c8": [
      3
    ],
    "14b68a54": [
      3
    ],
    "5d4ea611": [
      3
    ],
    "2fd16039": [
      3
    ],
    "23fa5e61": [
      3
    ],
    "9ae44b4e": [
      3
    ],
    "7839f732": [
      6
    ],
    "4c1a09ca": [
      6
    ],
    "702dacd4": [
      6
    ],
    "7bc54750": [
      3
    ],
    "80a73446": [
      3
    ],
    "4c566027": [
      3
    ],
    "c111410e": [
      3
    ],
    "505e2f23": [
      3
    ],
    "0c424ff8": [
      3
    ],
    "35460dd2": [
      3
    ],
    "4c13ef87": [
      3
    ],
    "5d4c2252": [
      3
    ],
    "7d363dca": [
      3
    ],
    "2584d514": [
      3
    ],
    "d04217e8": [
      3
    ],
    "605234e6": [
      3
    ],
    "a3d67b2a": [
      3
    ],
    "1119c128": [
      3
    ],
    "2dd602ed": [
      6
    ],
    "06651000": [
      6
    ],
    "c9512260": [
      3
    ],
    "e15138f2": [
      6
    ],
    "8f8e60ce": [
      6
    ],
    "da6a65d8": [
      6
    ],
    "324f97aa": [
      6
    ],
    "35679ebb": [
      6
    ],
    "5d20a3d2": [
      3
    ],
    "12e3f952": [
      3
    ],
    "63748d8d": [
      3
    ],
    "53ef6974": [
      3
    ],
    "ce9b2062": [
      3
    ],
    "8711e110": [
      3
    ],
    "ec45b0d4": [
      3
    ],
    "d3bd8a66": [
      3
    ],
    "46111e31": [
      3
    ],
    "02cbbf9a": [
      3
    ],
    "525e67b2": [
      3
    ],
    "64b53f68": [
      3
    ],
    "3c816d58": [
      3
    ],
    "40b19125": [
      3
    ],
    "f0f4d560": [
      3
    ],
    "a9de09ee": [
      3
    ],
    "ef9b0592": [
      3
    ],
    "f4c10934": [
      3
    ],
    "5b34de22": [
      3
    ],
    "44b56e22": [
      3
    ],
    "581beeca": [
      3
    ],
    "346ac89a": [
      3
    ],
    "179f68fb": [
      3
    ],
    "22530c5e": [
      3
    ],
    "4c60b3d4": [
      3
    ],
    "21c25586": [
      3
    ],
    "5023f954": [
      6
    ],
    "05787522": [
      6
    ],
    "1694edc2": [
      6
    ],
    "37df4952": [
      6
    ],
    "d69182ee": [
      6
    ],
    "6c64c0de": [
      3
    ],
    "fa329a96": [
      6
    ],
    "6a34e186": [
      6
    ],
    "125c7ba7": [
      6
    ],
    "9335f7ea": [
      3
    ],
    "b6507e2e": [
      3
    ],
    "0e62e320": [
      6
    ],
    "076d7614": [
      6
    ],
    "49692bc0": [
      3
    ],
    "3fa24a89": [
      3
    ],
    "2299dcb6": [
      3
    ],
    "07fef860": [
      3
    ],
    "1ba6d4f5": [
      3
    ],
    "08f7df50": [
      3
    ],
    "04902f9f": [
      3
    ],
    "11100b22": [
      3
    ],
    "20c38d56": [
      3
    ],
    "52c2c8d8": [
      3
    ],
    "7a32d1ea": [
      3
    ],
    "222f3db3": [
      3
    ],
    "89c95d14": [
      3
    ],
    "9b8a1e92": [
      3
    ],
    "a81aca42": [
      3
    ],
    "42975f6c": [
      3
    ],
    "9cb740d6": [
      3
    ],
    "8a7f427a": [
      3
    ],
    "8d0a1efc": [
      3
    ],
    "07261f26": [
      3
    ],
    "0a9aa60b": [
      3
    ],
    "ad726086": [
      3
    ],
    "0f70f173": [
      3
    ],
    "f937ac4a": [
      3
    ],
    "64781d2a": [
      3
    ],
    "3aa59038": [
      3
    ],
    "2cfa2fe6": [
      3
    ],
    "ea1d1a7a": [
      3
    ],
    "356dd47a": [
      3
    ],
    "662d04f9": [
      3
    ],
    "c8887c8a": [
      3
    ],
    "269ba8e5": [
      3
    ],
    "3f9bbc2a": [
      3
    ],
    "7602b96c": [
      3
    ],
    "d9d1a8f4": [
      3
    ],
    "48f36dfd": [
      3
    ],
    "07412cc8": [
      6
    ],
    "0f9a464a": [
      6
    ],
    "59ad3c30": [
      6
    ],
    "27ed0167": [
      6
    ],
    "b55544c8": [
      4
    ],
    "4afd2431": [
      4
    ],
    "049d5d37": [
      4
    ],
    "5a6948d2": [
      4
    ],
    "4dc81a1d": [
      4
    ],
    "0f339dac": [
      4
    ],
    "5b4fa469": [
      4
    ],
    "44ff429a": [
      4
    ],
    "bba006ae": [
      4
    ],
    "7fa6cf50": [
      4
    ]
  },
  "assetsMapping": {
    "6fca0322": [
      "1eafbd9.js"
    ],
    "085a35c4": [
      "346dfa5.js"
    ],
    "2a130dde": [
      "7256f7e.js"
    ],
    "1a3ae26b": [
      "d470d6c.js"
    ]
  }
}